<?xml version="1.0" encoding="utf-8"?>
<notes archive-path="roman/tipitaka (mula)/suttapitaka/anguttaranikaya/pancakanipatapali/(15) 5. tikandakivaggo-notes.xml">
  <note line="3" original="ādiyyamukho (sī.), ādeyyamukho (syā. kaṃ.), ādiyamukho (pī.) aṭṭhakathāya paṭhamasaṃvaṇṇanānurūpaṃ. pu. pa. 193 passitabbaṃ" reference-line="3" id="0">
    <extra> aṭṭhakathāya paṭhamasaṃvaṇṇanānurūpaṃ. pu. pa. 193 passitabbaṃ</extra>
    <alternatives>
      <alternative source-abbr="vri" source="vipassana research institut">ādheyyamukho</alternative>
      <alternative source-abbr="sī." source="sri lanka">ādiyyamukho</alternative>
      <alternative source-abbr="syā. kaṃ." source="syā. kaṃ.">ādeyyamukho</alternative>
      <alternative source-abbr="pī." source="pali text society">ādiyamukho</alternative>
    </alternatives>
    <type>auto</type>
    <previous>, bhikkhave, puggalā santo saṃvijjamānā lokasmiṃ. Katame pañca? Datvā avajānāti, saṃvāsena avajānāti, ādheyyamukho </previous>
  </note>
  <note line="13" original="mando hoti momūho (sī.)" reference-line="3" id="1">
    <extra></extra>
    <alternatives>
      <alternative source-abbr="vri" source="vipassana research institut">momūho hoti</alternative>
      <alternative source-abbr="sī." source="sri lanka">mando hoti momūho</alternative>
    </alternatives>
    <type>auto</type>
    <previous> hoti, lolo hoti, mando momūho hoti </previous>
  </note>
  <note line="21" original="adhimuccito (syā.)" reference-line="6" id="2">
    <extra></extra>
    <alternatives>
      <alternative source-abbr="vri" source="vipassana research institut">adhimuccitā</alternative>
      <alternative source-abbr="syā." source="thai">adhimuccito</alternative>
    </alternatives>
    <type>auto</type>
    <previous> hoti? Idha, bhikkhave, ekacco puggalo parassa vaṇṇe vā avaṇṇe vā bhāsiyamāne taṃ khippaññeva adhimuccitā </previous>
  </note>
  <note line="29" original="pu. pa. 191" reference-line="11" id="3">
    <type>raw</type>
  </note>
  <note line="32" original="ārabbhajā (pī. ka.), ārabhajā (syā. kaṃ.)" reference-line="15" id="4">
    <extra></extra>
    <alternatives>
      <alternative source-abbr="vri" source="vipassana research institut">ārambhajā</alternative>
      <alternative source-abbr="pī. ka." source="pī. ka.">ārabbhajā</alternative>
      <alternative source-abbr="syā. kaṃ." source="syā. kaṃ.">ārabhajā</alternative>
    </alternatives>
    <type>auto</type>
    <previous> nirujjhanti, so evamassa vacanīyo – ‘āyasmato kho ārambhajā </previous>
  </note>
  <note line="41" original="saṃvaḍḍhanti (ka.)" reference-line="15" id="5">
    <extra></extra>
    <alternatives>
      <alternative source-abbr="vri" source="vipassana research institut">pavaḍḍhanti</alternative>
      <alternative source-abbr="ka." source="cambodian">saṃvaḍḍhanti</alternative>
    </alternatives>
    <type>auto</type>
    <previous> āsavā saṃvijjanti, vippaṭisārajā āsavā pavaḍḍhanti </previous>
  </note>
  <note line="49" original="bhāvetuṃ (sī. pī.)" reference-line="15" id="6">
    <extra></extra>
    <alternatives>
      <alternative source-abbr="vri" source="vipassana research institut">bhāvetu</alternative>
      <alternative source-abbr="sī. pī." source="sī. pī.">bhāvetuṃ</alternative>
    </alternatives>
    <type>auto</type>
    <previous>, sādhu vatāyasmā ārambhaje āsave pahāya vippaṭisāraje āsave paṭivinodetvā cittaṃ paññañca bhāvetu </previous>
  </note>
  <note line="57" original="pu. pa. 191" reference-line="19" id="7">
    <type>raw</type>
  </note>
  <note line="60" original="pesesuṃ (syā. ka.)" reference-line="22" id="8">
    <extra></extra>
    <alternatives>
      <alternative source-abbr="vri" source="vipassana research institut">ṭhapesuṃ</alternative>
      <alternative source-abbr="syā. ka." source="syā. ka.">pesesuṃ</alternative>
    </alternatives>
    <type>auto</type>
    <previous> kho te licchavī magge purisaṃ ṭhapesuṃ </previous>
  </note>
  <note line="68" original="yathā tvaṃ (sī. pī.)" reference-line="22" id="9">
    <extra></extra>
    <alternatives>
      <alternative source-abbr="vri" source="vipassana research institut">yadā tvaṃ</alternative>
      <alternative source-abbr="sī. pī." source="sī. pī.">yathā tvaṃ</alternative>
    </alternatives>
    <type>auto</type>
    <previous> – yadā tvaṃ </previous>
  </note>
  <note line="76" original="kāmādhimuttānaṃ vata vo licchavīnaṃ (sī.), kāmādhimuttānaṃ vata vo licchavī (syā.), kāmādhimuttānaṃva vo licchavī (?)" reference-line="25" id="10">
    <extra></extra>
    <alternatives>
      <alternative source-abbr="vri" source="vipassana research institut">vata, bho, licchavīnaṃ</alternative>
      <alternative source-abbr="sī." source="sri lanka">kāmādhimuttānaṃ vata vo licchavīnaṃ</alternative>
      <alternative source-abbr="syā." source="thai">kāmādhimuttānaṃ vata vo licchavī</alternative>
      <alternative source-abbr="?" source="unknown">kāmādhimuttānaṃva vo licchavī</alternative>
    </alternatives>
    <type>auto</type>
    <previous> vata, bho, licchavīnaṃ </previous>
  </note>
  <note line="86" original="viññātassa (sī. pī.) a. ni. 5.195" reference-line="25" id="11">
    <extra> a. ni. 5.195</extra>
    <alternatives>
      <alternative source-abbr="vri" source="vipassana research institut">viññātā</alternative>
      <alternative source-abbr="sī. pī." source="sī. pī.">viññātassa</alternative>
    </alternatives>
    <type>auto</type>
    <previous> desetā puggalo dullabho lokasmiṃ, tathāgatappaveditassa dhammavinayassa desitassa viññātā puggalo dullabho lokasmiṃ, tathāgatappaveditassa dhammavinayassa desitassa viññātā </previous>
  </note>
  <note line="94" original="kaṇḍakīvane (saṃ. ni. 5.902)" reference-line="27" id="12">
    <extra></extra>
    <alternatives>
      <alternative source-abbr="vri" source="vipassana research institut">tikaṇḍakīvane</alternative>
      <alternative source-abbr="saṃ. ni. 5.902" source="saṃ. ni. 5.902">kaṇḍakīvane</alternative>
    </alternatives>
    <type>auto</type>
    <previous> Ekaṃ samayaṃ bhagavā sākete viharati tikaṇḍakīvane </previous>
  </note>
  <note line="102" original="appaṭikkūle paṭikkūlasaññī (sī. syā. kaṃ. pī.)" reference-line="28" id="13">
    <extra></extra>
    <alternatives>
      <alternative source-abbr="vri" source="vipassana research institut">appaṭikūle paṭikūlasaññī</alternative>
      <alternative source-abbr="sī. syā. kaṃ. pī." source="sī. syā. kaṃ. pī.">appaṭikkūle paṭikkūlasaññī</alternative>
    </alternatives>
    <type>auto</type>
    <previous>Sādhu, bhikkhave, bhikkhu kālena kālaṃ appaṭikūle paṭikūlasaññī </previous>
  </note>
  <note line="110" original="kathañca (sī. pī. ka.)" reference-line="29" id="14">
    <extra></extra>
    <alternatives>
      <alternative source-abbr="vri" source="vipassana research institut">Kiñca</alternative>
      <alternative source-abbr="sī. pī. ka." source="sī. pī. ka.">kathañca</alternative>
    </alternatives>
    <type>auto</type>
    <previous>Kiñca </previous>
  </note>
  <note line="118" original="kvacini (sī. syā. pī.)" reference-line="33" id="15">
    <extra></extra>
    <alternatives>
      <alternative source-abbr="vri" source="vipassana research institut">kvacani</alternative>
      <alternative source-abbr="sī. syā. pī." source="sī. syā. pī.">kvacini</alternative>
    </alternatives>
    <type>auto</type>
    <previous> kvacani </previous>
  </note>
  <note line="126" original="kiñcana (sī. pī.)" reference-line="33" id="16">
    <extra></extra>
    <alternatives>
      <alternative source-abbr="vri" source="vipassana research institut">kiñcanaṃ</alternative>
      <alternative source-abbr="sī. pī." source="sī. pī.">kiñcana</alternative>
    </alternatives>
    <type>auto</type>
    <previous> katthaci kiñcanaṃ </previous>
  </note>
  <note line="134" original="avatthānacārikaṃ (syā.)" reference-line="38" id="17">
    <extra></extra>
    <alternatives>
      <alternative source-abbr="vri" source="vipassana research institut">anavatthacārikaṃ</alternative>
      <alternative source-abbr="syā." source="thai">avatthānacārikaṃ</alternative>
    </alternatives>
    <type>auto</type>
    <previous> Pañcahi, bhikkhave, dhammehi samannāgato bhikkhu mitto na sevitabbo. Katamehi pañcahi? Kammantaṃ kāreti, adhikaraṇaṃ ādiyati, pāmokkhesu bhikkhūsu paṭiviruddho hoti, dīghacārikaṃ anavatthacārikaṃ </previous>
  </note>
  <note line="142" original="acittikatvā (pī.), acitiṃ katvā (syā.), acittiṃ katvā (ka.)" reference-line="41" id="18">
    <extra></extra>
    <alternatives>
      <alternative source-abbr="vri" source="vipassana research institut">acittīkatvā</alternative>
      <alternative source-abbr="pī." source="pali text society">acittikatvā</alternative>
      <alternative source-abbr="syā." source="thai">acitiṃ katvā</alternative>
      <alternative source-abbr="ka." source="cambodian">acittiṃ katvā</alternative>
    </alternatives>
    <type>auto</type>
    <previous> Pañcimāni, bhikkhave, asappurisadānāni. Katamāni pañca? Asakkaccaṃ deti, acittīkatvā </previous>
  </note>
  <note line="152" original="apaviṭṭaṃ (syā. kaṃ.)" reference-line="41" id="19">
    <extra></extra>
    <alternatives>
      <alternative source-abbr="vri" source="vipassana research institut">apaviddhaṃ</alternative>
      <alternative source-abbr="syā. kaṃ." source="syā. kaṃ.">apaviṭṭaṃ</alternative>
    </alternatives>
    <type>auto</type>
    <previous> deti, asahatthā deti, apaviddhaṃ </previous>
  </note>
  <note line="160" original="anaggahitacitto (sī.)" reference-line="44" id="20">
    <extra></extra>
    <alternatives>
      <alternative source-abbr="vri" source="vipassana research institut">anuggahitacitto</alternative>
      <alternative source-abbr="sī." source="sri lanka">anaggahitacitto</alternative>
    </alternatives>
    <type>auto</type>
    <previous>, bhikkhave, sappurisadānāni. Katamāni pañca? Saddhāya dānaṃ deti, sakkaccaṃ dānaṃ deti, kālena dānaṃ deti, anuggahitacitto </previous>
  </note>
  <note line="168" original="kammakārāti (ka.)" reference-line="46" id="21">
    <extra></extra>
    <alternatives>
      <alternative source-abbr="vri" source="vipassana research institut">kammakarāti</alternative>
      <alternative source-abbr="ka." source="cambodian">kammakārāti</alternative>
    </alternatives>
    <type>auto</type>
    <previous>Sakkaccaṃ kho pana, bhikkhave, dānaṃ datvā yattha yattha tassa dānassa vipāko nibbattati, aḍḍho ca hoti mahaddhano mahābhogo. Yepissa te honti puttāti vā dārāti vā dāsāti vā pessāti vā kammakarāti </previous>
  </note>
  <note line="176" original="appiyato vā dāyādato vā (sī. syā. kaṃ. pī.), appiyadāyādato vā (ka.)" reference-line="49" id="22">
    <extra></extra>
    <alternatives>
      <alternative source-abbr="vri" source="vipassana research institut">appiyato vā dāyādato vā</alternative>
      <alternative source-abbr="sī. syā. kaṃ. pī." source="sī. syā. kaṃ. pī.">appiyato vā dāyādato vā</alternative>
      <alternative source-abbr="ka." source="cambodian">appiyadāyādato vā</alternative>
    </alternatives>
    <type>auto</type>
    <previous> parañca anupahacca kho pana, bhikkhave, dānaṃ datvā yattha yattha tassa dānassa vipāko nibbattati, aḍḍho ca hoti mahaddhano mahābhogo; na cassa kutoci bhogānaṃ upaghāto āgacchati aggito vā udakato vā rājato vā corato vā appiyato vā dāyādato vā </previous>
  </note>
  <note line="185" original="kathā. 267" reference-line="54" id="23">
    <type>raw</type>
  </note>
</notes>
