<?xml version="1.0" encoding="utf-8"?>
<notes archive-path="roman/tipitaka (mula)/suttapitaka/khuddakanikaya/dhammapadapali/23. nagavaggo-notes.xml">
  <note line="3" original="ājānīyāva (syā.)" reference-line="9" id="0">
    <extra></extra>
    <alternatives>
      <alternative source-abbr="syā." source="thai">ājānīyāva</alternative>
    </alternatives>
    <type>no_match</type>
    <previous> Varamassatarā dantā, ājānīyā ca </previous>
  </note>
  <note line="10" original="kuñjarāva (syā.)" reference-line="10" id="1">
    <extra></extra>
    <alternatives>
      <alternative source-abbr="syā." source="thai">kuñjarāva</alternative>
    </alternatives>
    <type>no_match</type>
    <previous>Kuñjarā ca </previous>
  </note>
  <note line="17" original="dhanapālako (sī. syā. kaṃ. pī.)" reference-line="15" id="2">
    <extra></extra>
    <alternatives>
      <alternative source-abbr="vri" source="vipassana research institut">Dhanapālo</alternative>
      <alternative source-abbr="sī. syā. kaṃ. pī." source="sī. syā. kaṃ. pī.">dhanapālako</alternative>
    </alternatives>
    <type>auto</type>
    <previous> Dhanapālo </previous>
  </note>
  <note line="25" original="kaṭukappabhedano (sī. syā. pī.)" reference-line="15" id="3">
    <extra></extra>
    <alternatives>
      <alternative source-abbr="vri" source="vipassana research institut">kaṭukabhedano</alternative>
      <alternative source-abbr="sī. syā. pī." source="sī. syā. pī.">kaṭukappabhedano</alternative>
    </alternatives>
    <type>auto</type>
    <previous> nāma kuñjaro, kaṭukabhedano </previous>
  </note>
  <note line="33" original="susarati (ka.)" reference-line="16" id="4">
    <extra></extra>
    <alternatives>
      <alternative source-abbr="vri" source="vipassana research institut">sumarati</alternative>
      <alternative source-abbr="ka." source="cambodian">susarati</alternative>
    </alternatives>
    <type>auto</type>
    <previous>Baddho kabaḷaṃ na bhuñjati, sumarati </previous>
  </note>
  <note line="41" original="sattova (sī. pī.)" reference-line="25" id="5">
    <extra></extra>
    <alternatives>
      <alternative source-abbr="vri" source="vipassana research institut">sannova</alternative>
      <alternative source-abbr="sī. pī." source="sī. pī.">sattova</alternative>
    </alternatives>
    <type>auto</type>
    <previous>Duggā uddharathattānaṃ, paṅke sannova </previous>
  </note>
</notes>
