<?xml version="1.0" encoding="utf-8"?>
<notes archive-path="roman/tipitaka (mula)/suttapitaka/khuddakanikaya/khuddakapathapali/5. mangalasuttam-notes.xml">
  <note line="3" original="pūjanīyānaṃ (sī. syā. kaṃ. pī.)" reference-line="8" id="0">
    <extra></extra>
    <alternatives>
      <alternative source-abbr="vri" source="vipassana research institut">pūjaneyyānaṃ</alternative>
      <alternative source-abbr="sī." source="sri lanka">pūjanīyānaṃ</alternative>
      <alternative source-abbr="syā." source="thai">pūjanīyānaṃ</alternative>
      <alternative source-abbr="kaṃ." source="kaṃ.">pūjanīyānaṃ</alternative>
      <alternative source-abbr="pī." source="pali text society">pūjanīyānaṃ</alternative>
    </alternatives>
    <type>auto</type>
    <previous>Pūjā ca pūjaneyyānaṃ </previous>
  </note>
  <note line="15" original="atthasammāpaṇīdhī (katthaci)" reference-line="11" id="1">
    <extra></extra>
    <alternatives>
      <alternative source-abbr="vri" source="vipassana research institut">Attasammāpaṇidhi</alternative>
      <alternative source-abbr="katthaci" source="katthaci">atthasammāpaṇīdhī</alternative>
    </alternatives>
    <type>auto</type>
    <previous>Attasammāpaṇidhi </previous>
  </note>
  <note line="24" original="dhammassāvaṇaṃ (ka. sī.), dhammasavanaṃ (ka. sī.)" reference-line="26" id="2">
    <extra></extra>
    <alternatives>
      <alternative source-abbr="vri" source="vipassana research institut">dhammassavanaṃ</alternative>
      <alternative source-abbr="ka." source="cambodian">dhammassāvaṇaṃ</alternative>
      <alternative source-abbr="sī." source="sri lanka">dhammassāvaṇaṃ</alternative>
      <alternative source-abbr="ka." source="cambodian">dhammasavanaṃ</alternative>
      <alternative source-abbr="sī." source="sri lanka">dhammasavanaṃ</alternative>
    </alternatives>
    <type>auto</type>
    <previous>Kālena dhammassavanaṃ </previous>
  </note>
</notes>
