<notes archive-path="/mula/suttapitaka/anguttaranikaya/dasakanipatapali/(20) 5.aparapuggalavaggo">
  <note reference-line="5" id="0">
    <original>nābhibhoti (sī.) a. ni. 10.156-166</original>
    <type>raw</type>
    <snippet> ‘‘Dasahi, bhikkhave, dhammehi samannāgato puggalo na bhajitabbo…pe… bhajitabbo… na payirupāsitabbo… payirupāsitabbo… na pujjo hoti… pujjo hoti… na pāsaṃso hoti… pāsaṃso hoti… agāravo hoti… gāravo hoti… appatisso hoti… sappatisso hoti… na ārādhako hoti… ārādhako hoti… na visujjhati… visujjhati… mānaṃ nādhibhoti </snippet>
  </note>
</notes>
